Workbook

Sheet RetailSales
A1: Order ID | B1: Invoice ID | C1: Order Date | D1: Month | E1: City | F1: Customer ID | G1: Customer Name | H1: Gender | I1: Customer Type | J1: Product Category | K1: Product Name | L1: Brand | M1: Quantity | N1: Unit Price | O1: Discount % | P1: Sales | Q1: Cost | R1: Profit | S1: Payment Mode | T1: Customer Rating | U1: Delivery Status | V1: Sales Executive | W1: Profit Margin% | X1: Customer Segment | Y1: order Size | Z1: Day
A2: ORD1001 | B2: INV5001 | C2: 46162 | D2: May | E2: Faridabad | F2: CUST2042 | G2: Aditi Gupta | H2: Female | I2: Retail | J2: Window Cooler | K2: Ozone | L2: Crompton | M2: 2 | N2: 11747 | O2: 15 | P2: 19969.9 | Q2: 16132.93 | R2: 3836.97 | S2: UPI | T2: 3 | U2: In Transit | V2: Priya | W2: =Table1[[#This Row],[Profit]]/Table1[[#This Row],[Sales]] -> 0.19213767 | X2: =IF(Table1[[#This Row],[Sales]]>=30000,"High Value",IF(Table1[[#This Row],[Sales]]>=15000,"Medium Value","Low Value")) -> Medium Value | Y2: =IF(Table1[[#This Row],[Quantity]]>=3,"Bulk Order","Regular Order") -> Regular Order | Z2: =TEXT(Table1[[#This Row],[Order Date]],"dddd") -> Wednesday
A3: ORD1002 | B3: INV5002 | C3: 46184 | D3: June | E3: Muradabad | F3: CUST2135 | G3: Dev Sharma | H3: Male | I3: Retail | J3: Personal Cooler | K3: PX97 Torque | L3: Bajaj | M3: 1 | N3: 7402 | O3: 10 | P3: 6661.8 | Q3: 5321.62 | R3: 1340.18 | S3: Cash | T3: 4 | U3: Delivered | V3: Neha | W3: =Table1[[#This Row],[Profit]]/Table1[[#This Row],[Sales]] -> 0.20117386 | X3: =IF(Table1[[#This Row],[Sales]]>=30000,"High Value",IF(Table1[[#This Row],[Sales]]>=15000,"Medium Value","Low Value")) -> Low Value | Y3: =IF(Table1[[#This Row],[Quantity]]>=3,"Bulk Order","Regular Order") -> Regular Order | Z3: =TEXT(Table1[[#This Row],[Order Date]],"dddd") -> Thursday
A4: ORD1003 | B4: INV5003 | C4: 46158 | D4: May | E4: Ghaziabad | F4: CUST2115 | G4: Yash Gupta | H4: Male | I4: Dealer | J4: Desert Cooler | K4: Symphony Diet 35T | L4: Symphony | M4: 4 | N4: 16407 | O4: 0 | P4: 65628 | Q4: 51271.85 | R4: 14356.15 | S4: Bank Transfer | T4: 4 | U4: In Transit | V4: Rahul | W4: =Table1[[#This Row],[Profit]]/Table1[[#This Row],[Sales]] -> 0.21875038 | X4: =IF(Table1[[#This Row],[Sales]]>=30000,"High Value",IF(Table1[[#This Row],[Sales]]>=15000,"Medium Value","Low Value")) -> High Value | Y4: =IF(Table1[[#This Row],[Quantity]]>=3,"Bulk Order","Regular Order") -> Bulk Order | Z4: =TEXT(Table1[[#This Row],[Order Date]],"dddd") -> Saturday
A5: ORD1004 | B5: INV5004 | C5: 46156 | D5: May | E5: Meerut | F5: CUST2177 | G5: Mehak Sharma | H5: Female | I5: Retail | J5: Personal Cooler | K5: Fresco | L5: Orient | M5: 1 | N5: 7676 | O5: 5 | P5: 7292.2 | Q5: 5947.31 | R5: 1344.89 | S5: UPI | T5: 5 | U5: Delivered | V5: Neha | W5: =Table1[[#This Row],[Profit]]/Table1[[#This Row],[Sales]] -> 0.18442857 | X5: =IF(Table1[[#This Row],[Sales]]>=30000,"High Value",IF(Table1[[#This Row],[Sales]]>=15000,"Medium Value","Low Value")) -> Low Value | Y5: =IF(Table1[[#This Row],[Quantity]]>=3,"Bulk Order","Regular Order") -> Regular Order | Z5: =TEXT(Table1[[#This Row],[Order Date]],"dddd") -> Thursday
A6: ORD1005 | B6: INV5005 | C6: 46163 | D6: May | E6: Meerut | F6: CUST2173 | G6: Saurabh Sharma | H6: Male | I6: Retail | J6: Desert Cooler | K6: Symphony Diet 35T | L6: Symphony | M6: 2 | N6: 15670 | O6: 10 | P6: 28206 | Q6: 22427.66 | R6: 5778.34 | S6: Cash | T6: 5 | U6: In Transit | V6: Mohit | W6: =Table1[[#This Row],[Profit]]/Table1[[#This Row],[Sales]] -> 0.20486209 | X6: =IF(Table1[[#This Row],[Sales]]>=30000,"High Value",IF(Table1[[#This Row],[Sales]]>=15000,"Medium Value","Low Value")) -> Medium Value | Y6: =IF(Table1[[#This Row],[Quantity]]>=3,"Bulk Order","Regular Order") -> Regular Order | Z6: =TEXT(Table1[[#This Row],[Order Date]],"dddd") -> Thursday
A7: ORD1006 | B7: INV5006 | C7: 46151 | D7: May | E7: Greater Noida | F7: CUST2072 | G7: Aditya Jain | H7: Male | I7: Retail | J7: Personal Cooler | K7: PX97 Torque | L7: Bajaj | M7: 2 | N7: 7197 | O7: 5 | P7: 13674.3 | Q7: 11183.2 | R7: 2491.1 | S7: Card | T7: 4 | U7: Delivered | V7: Rahul | W7: =Table1[[#This Row],[Profit]]/Table1[[#This Row],[Sales]] -> 0.18217386 | X7: =IF(Table1[[#This Row],[Sales]]>=30000,"High Value",IF(Table1[[#This Row],[Sales]]>=15000,"Medium Value","Low Value")) -> Low Value | Y7: =IF(Table1[[#This Row],[Quantity]]>=3,"Bulk Order","Regular Order") -> Regular Order | Z7: =TEXT(Table1[[#This Row],[Order Date]],"dddd") -> Saturday
A8: ORD1007 | B8: INV5007 | C8: 46145 | D8: May | E8: Muradabad | F8: CUST2165 | G8: Pooja Jain | H8: Female | I8: Dealer | J8: Desert Cooler | K8: Symphony Diet 35T | L8: Symphony | M8: 4 | N8: 16768 | O8: 5 | P8: 63718.4 | Q8: 52190.97 | R8: 11527.43 | S8: Cash | T8: 5 | U8: Delivered | V8: Aman | W8: =Table1[[#This Row],[Profit]]/Table1[[#This Row],[Sales]] -> 0.18091211 | X8: =IF(Table1[[#This Row],[Sales]]>=30000,"High Value",IF(Table1[[#This Row],[Sales]]>=15000,"Medium Value","Low Value")) -> High Value | Y8: =IF(Table1[[#This Row],[Quantity]]>=3,"Bulk Order","Regular Order") -> Bulk Order | Z8: =TEXT(Table1[[#This Row],[Order Date]],"dddd") -> Sunday
A9: ORD1008 | B9: INV5008 | C9: 46180 | D9: June | E9: Ghaziabad | F9: CUST2066 | G9: Mehak Sharma | H9: Female | I9: Retail | J9: Desert Cooler | K9: Symphony Diet 35T | L9: Symphony | M9: 1 | N9: 16158 | O9: 5 | P9: 15350.1 | Q9: 12341.63 | R9: 3008.47 | S9: Card | T9: 5 | U9: Cancelled | V9: Rahul | W9: =Table1[[#This Row],[Profit]]/Table1[[#This Row],[Sales]] -> 0.19599025 | X9: =IF(Table1[[#This Row],[Sales]]>=30000,"High Value",IF(Table1[[#This Row],[Sales]]>=15000,"Medium Value","Low Value")) -> Medium Value | Y9: =IF(Table1[[#This Row],[Quantity]]>=3,"Bulk Order","Regular Order") -> Regular Order | Z9: =TEXT(Table1[[#This Row],[Order Date]],"dddd") -> Sunday
A10: ORD1009 | B10: INV5009 | C10: 46154 | D10: May | E10: Faridabad | F10: CUST2003 | G10: Nikhil Arora | H10: Male | I10: Dealer | J10: Desert Cooler | K10: Optimus 100 | L10: Crompton | M10: 4 | N10: 16018 | O10: 10 | P10: 57664.8 | Q10: 45758.79 | R10: 11906.01 | S10: UPI | T10: 4 | U10: Delivered | V10: Priya | W10: =Table1[[#This Row],[Profit]]/Table1[[#This Row],[Sales]] -> 0.20646928 | X10: =IF(Table1[[#This Row],[Sales]]>=30000,"High Value",IF(Table1[[#This Row],[Sales]]>=15000,"Medium Value","Low Value")) -> High Value | Y10: =IF(Table1[[#This Row],[Quantity]]>=3,"Bulk Order","Regular Order") -> Bulk Order | Z10: =TEXT(Table1[[#This Row],[Order Date]],"dddd") -> Tuesday
A11: ORD1010 | B11: INV5010 | C11: 46157 | D11: May | E11: Greater Noida | F11: CUST2166 | G11: Tushar Singh | H11: Male | I11: Dealer | J11: Desert Cooler | K11: Symphony Diet 35T | L11: Symphony | M11: 3 | N11: 16295 | O11: 5 | P11: 46440.75 | Q11: 37012.84 | R11: 9427.91 | S11: Card | T11: 5 | U11: Delivered | V11: Aman | W11: =Table1[[#This Row],[Profit]]/Table1[[#This Row],[Sales]] -> 0.20300943 | X11: =IF(Table1[[#This Row],[Sales]]>=30000,"High Value",IF(Table1[[#This Row],[Sales]]>=15000,"Medium Value","Low Value")) -> High Value | Y11: =IF(Table1[[#This Row],[Quantity]]>=3,"Bulk Order","Regular Order") -> Bulk Order | Z11: =TEXT(Table1[[#This Row],[Order Date]],"dddd") -> Friday
A12: ORD1011 | B12: INV5011 | C12: 46203 | D12: June | E12: Hapur | F12: CUST2088 | G12: Nikita Kapoor | H12: Female | I12: Dealer | J12: Desert Cooler | K12: Symphony Diet 35T | L12: Symphony | M12: 4 | N12: 16729 | O12: 0 | P12: 66916 | Q12: 53425 | R12: 13491 | S12: UPI | T12: 4 | U12: Delivered | V12: Neha | W12: =Table1[[#This Row],[Profit]]/Table1[[#This Row],[Sales]] -> 0.20161097 | X12: =IF(Table1[[#This Row],[Sales]]>=30000,"High Value",IF(Table1[[#This Row],[Sales]]>=15000,"Medium Value","Low Value")) -> High Value | Y12: =IF(Table1[[#This Row],[Quantity]]>=3,"Bulk Order","Regular Order") -> Bulk Order | Z12: =TEXT(Table1[[#This Row],[Order Date]],"dddd") -> Tuesday
A13: ORD1012 | B13: INV5012 | C13: 46143 | D13: May | E13: Greater Noida | F13: CUST2130 | G13: Shreya Kapoor | H13: Female | I13: Retail | J13: Personal Cooler | K13: PX97 Torque | L13: Bajaj | M13: 2 | N13: 8290 | O13: 10 | P13: 14922 | Q13: 12133.01 | R13: 2788.99 | S13: UPI | T13: 5 | U13: Delivered | V13: Priya | W13: =Table1[[#This Row],[Profit]]/Table1[[#This Row],[Sales]] -> 0.18690457 | X13: =IF(Table1[[#This Row],[Sales]]>=30000,"High Value",IF(Table1[[#This Row],[Sales]]>=15000,"Medium Value","Low Value")) -> Low Value | Y13: =IF(Table1[[#This Row],[Quantity]]>=3,"Bulk Order","Regular Order") -> Regular Order | Z13: =TEXT(Table1[[#This Row],[Order Date]],"dddd") -> Friday
... A501: ORD1500 | B501: INV5500 | C501: 46151 | D501: May | E501: Ghaziabad | F501: CUST2089 | G501: Shreya Kapoor | H501: Female | I501: Dealer | J501: Tower Cooler | K501: TallDe | L501: Kenstar | M501: 4 | N501: 10585 | O501: 5 | P501: 40223 | Q501: 32076.13 | R501: 8146.87 | S501: UPI | T501: 4 | U501: Delivered | V501: Neha | W501: =Table1[[#This Row],[Profit]]/Table1[[#This Row],[Sales]] -> 0.20254258 | X501: =IF(Table1[[#This Row],[Sales]]>=30000,"High Value",IF(Table1[[#This Row],[Sales]]>=15000,"Medium Value","Low Value")) -> High Value | Y501: =IF(Table1[[#This Row],[Quantity]]>=3,"Bulk Order","Regular Order") -> Bulk Order | Z501: =TEXT(Table1[[#This Row],[Order Date]],"dddd") -> Saturday

Sheet Data Cleaning
A1: Data Quality Check | B1: Result
A2: Total Records | B2: 500
A3: Total Columns | B3: 26
A4: Missing Values | B4: 0
A5: Duplicate Records | B5: 0
A6: Date Format | B6: dd-mmm-yyyy (Excel date)
A7: Data Types Checked | B7: Yes
A8: Outliers Checked | B8: Basic range validation performed
A9: Data Cleaning Status | B9: Completed

Sheet Analysis
A1: Metric | B1: Value
A2: Total Revenue | B2: =SUM(Table1[Sales]) -> 12482584 | D2: Notes
A3: Total Profit | B3: =SUM(Table1[Profit]) -> 2515406.7 | D3: Profit Margin = Total Profit ÷ Total Revenue
A4: Total Orders | B4: =COUNTA(Table1[Order ID]) -> 500 | D4: Total Customers = unique Customer IDs
A5: Average Order Value | B5: =AVERAGE(Table1[Sales]) -> 24965.169 | D5: Segment counts are order-level because Customer Segment is calculated from order Sales.
A6: Profit Margin | B6: =SUM(Table1[Profit])/SUM(Table1[Sales]) -> 0.20151329
A7: Total Customers | B7: =SUMPRODUCT((Table1[Customer ID]<>"")/COUNTIF(Table1[Customer ID],Table1[Customer ID]&"")) -> 167
A8: High Value Orders | B8: =COUNTIF(Table1[Customer Segment],"High Value") -> 155
A9: Medium Value Orders | B9: =COUNTIF(Table1[Customer Segment],"Medium Value") -> 174
A10: Low Value Orders | B10: =COUNTIF(Table1[Customer Segment],"Low Value") -> 171

Sheet Pivot_Month
A3: Month | B3: Sum of Sales
A4: May | B4: 6590173.2
A5: June | B5: 5892411.1
A6: Total Result | B6: 12482584

Sheet Pivot_City
A3: City | B3: Sum of Sales
A4: Ghaziabad | B4: 3513527.2
A5: Noida | B5: 2267410.2
A6: Greater Noida | B6: 1965270.2
A7: Meerut | B7: 1573718.6
A8: Muradabad | B8: 1289030.7
A9: Faridabad | B9: 1240942.9
A10: Hapur | B10: 424820.75
A11: Modinagar | B11: 207863.75
A12: Total Result | B12: 12482584

Sheet Pivot_Brand
A3: Brand | B3: Sum of Sales
A4: Symphony | B4: 5037684
A5: Crompton | B5: 3573863
A6: Kenstar | B6: 1400463.9
A7: Bajaj | B7: 1366633.6
A8: Orient | B8: 980083.65
A9: V-Guard | B9: 98515.4
A10: Generic | B10: 25340.85
A11: Total Result | B11: 12482584

Sheet Pivot_Product
A3: Product Name | B3: Sum of Sales
A4: Symphony Diet 35T | B4: 5037684
A5: Optimus 100 | B5: 2836458.9
A6: TallDe | B6: 1400463.9
A7: PX97 Torque | B7: 1366633.6
A8: Fresco | B8: 980083.65
A9: Total Result | B9: 12482584

Sheet Pivot_Payment
A3: Payment Mode | B3: Sum of Sales
A4: Bank Transfer | B4: 679739.8
A5: Card | B5: 2522406.5
A6: Cash | B6: 3576878.6
A7: UPI | B7: 5703559.5
A8: Total Result | B8: 12482584

Sheet Pivot_CustomerSegment
A3: Customer Segment | B3: Count of Order ID
A4: High Value | B4: 155
A5: Low Value | B5: 171
A6: Medium Value | B6: 174
A7: Total Result | B7: 500

Sheet Pivot_SalesExecutive
A3: Sales Executive | B3: Sum of Sales
A4: Aman | B4: 2414254.9
A5: Priya | B5: 2235484.5
A6: Neha | B6: 2112298.3
A7: Rahul | B7: 1958579.2
A8: Karan | B8: 1907075.1
A9: Mohit | B9: 1854892.4
A10: Total Result | B10: 12482584

Sheet Dashboard
A1: Retail Sales Performance Analysis Dashboard
A3: Total Revenue | D3: Total Profit | G3: Total Orders | J3: Average Order Value | M3: Profit Margin
A4: =Analysis!B2 -> 12482584 | D4: =Analysis!B3 -> 2515406.7 | G4: =Analysis!B4 -> 500 | J4: =Analysis!B5 -> 24965.169 | M4: =Analysis!B6 -> 0.20151329
A7: Dashboard Filters
A8: Month | D8: City | G8: Brand | J8: Customer Segment
A9: All | D9: All | G9: All | J9: All
